readme_cli/__init__.py
readme_cli/__main__.py
readme_cli/main.py
readme_cli/readme_cli.py
readme_cli/scroll.py
readme_cli/utilities.py
read_me_cli-0.2.1.dist-info/LICENSE
read_me_cli-0.2.1.dist-info/METADATA
read_me_cli-0.2.1.dist-info/WHEEL
read_me_cli-0.2.1.dist-info/entry_points.txt
read_me_cli-0.2.1.dist-info/top_level.txt
read_me_cli-0.2.1.dist-info/RECORD
