Metadata-Version: 2.1
Name: read-me-cli
Version: 0.2.1
Summary: Command line tool that displays github README.md content for github repositories
Home-page: https://github.com/Genza999/readme_cli
Author: Kisekka David
Author-email: cartpix@gmail.com
License: MIT
Keywords: readme cli readme.md github repository
Platform: UNKNOWN
Classifier: Development Status :: 2 - Pre-Alpha
Classifier: License :: OSI Approved :: MIT License
Classifier: Programming Language :: Python
Classifier: Programming Language :: Python :: 2
Classifier: Programming Language :: Python :: 2.7
Classifier: Programming Language :: Python :: 3
Classifier: Programming Language :: Python :: 3.4
Classifier: Programming Language :: Python :: 3.5
Classifier: Programming Language :: Python :: 3.6
Classifier: Programming Language :: Python :: 3.7
Requires-Python: >=3
Requires-Dist: beautifulsoup4 (==4.9.3)
Requires-Dist: certifi (==2020.6.20)
Requires-Dist: chardet (==3.0.4)
Requires-Dist: idna (==2.10)
Requires-Dist: requests (==2.24.0)
Requires-Dist: soupsieve (==2.0.1)
Requires-Dist: urllib3 (==1.25.10)
Requires-Dist: urwid (==2.1.2)
